pyconn/__init__.py
pyconn/api.py
pyconn/client/__init__.py
pyconn/client/db/__init__.py
pyconn/client/db/base.py
pyconn/client/db/bigquery.py
pyconn/client/db/mysql.py
pyconn/client/db/postgresql.py
pyconn/client/db/sqlite.py
pyconn/client/lake/__init__.py
pyconn/client/lake/base.py
pyconn/client/lake/gcs.py
pyconn/client/lake/s3.py
pyconn/constant/__init__.py
pyconn/constant/db_layer.py
pyconn/errors/__init__.py
pyconn/errors/base.py
pyconn/errors/params.py
pyconn/model/__init__.py
pyconn/model/meta_data.py
pyconn/model/native.py
pyconn/ops/__init__.py
pyconn/ops/io/__init__.py
pyconn/ops/io/export.py
pyconn/ops/sync/__init__.py
pyconn/ops/sync/base.py
pyconn/ops/sync/full.py
pyconn/ops/sync/general.py
pyconn/ops/sync/upsert.py
pyconn/utils/__init__.py
pyconn/utils/db_utils.py
pyconn/utils/misc.py
pyconn/utils/validator.py
python_connect-0.1.1.3.dist-info/LICENSE
python_connect-0.1.1.3.dist-info/METADATA
python_connect-0.1.1.3.dist-info/WHEEL
python_connect-0.1.1.3.dist-info/RECORD
